main.py
setup.py
byted_flux.egg-info/PKG-INFO
byted_flux.egg-info/SOURCES.txt
byted_flux.egg-info/dependency_links.txt
byted_flux.egg-info/requires.txt
byted_flux.egg-info/top_level.txt